ably/__init__.py
ably/http/__init__.py
ably/http/http.py
ably/http/httputils.py
ably/http/paginatedresult.py
ably/realtime/__init__.py
ably/realtime/connection.py
ably/realtime/connectionmanager.py
ably/realtime/realtime.py
ably/realtime/realtime_channel.py
ably/rest/__init__.py
ably/rest/auth.py
ably/rest/channel.py
ably/rest/push.py
ably/rest/rest.py
ably/scripts/__init__.py
ably/scripts/unasync.py
ably/sync/__init__.py
ably/sync/http/__init__.py
ably/sync/http/http.py
ably/sync/http/httputils.py
ably/sync/http/paginatedresult.py
ably/sync/realtime/__init__.py
ably/sync/realtime/connection.py
ably/sync/realtime/connectionmanager.py
ably/sync/realtime/realtime.py
ably/sync/realtime/realtime_channel.py
ably/sync/rest/__init__.py
ably/sync/rest/auth.py
ably/sync/rest/channel.py
ably/sync/rest/push.py
ably/sync/rest/rest.py
ably/sync/scripts/__init__.py
ably/sync/scripts/unasync.py
ably/sync/transport/__init__.py
ably/sync/transport/defaults.py
ably/sync/transport/websockettransport.py
ably/sync/types/__init__.py
ably/sync/types/authoptions.py
ably/sync/types/capability.py
ably/sync/types/channeldetails.py
ably/sync/types/channelstate.py
ably/sync/types/channelsubscription.py
ably/sync/types/connectiondetails.py
ably/sync/types/connectionerrors.py
ably/sync/types/connectionstate.py
ably/sync/types/device.py
ably/sync/types/flags.py
ably/sync/types/message.py
ably/sync/types/mixins.py
ably/sync/types/options.py
ably/sync/types/presence.py
ably/sync/types/stats.py
ably/sync/types/tokendetails.py
ably/sync/types/tokenrequest.py
ably/sync/types/typedbuffer.py
ably/sync/util/__init__.py
ably/sync/util/case.py
ably/sync/util/crypto.py
ably/sync/util/eventemitter.py
ably/sync/util/exceptions.py
ably/sync/util/helper.py
ably/sync/util/nocrypto.py
ably/sync/vcdiff/__init__.py
ably/sync/vcdiff/default_vcdiff_decoder.py
ably/transport/__init__.py
ably/transport/defaults.py
ably/transport/websockettransport.py
ably/types/__init__.py
ably/types/authoptions.py
ably-2.1.3.dist-info/METADATA
ably-2.1.3.dist-info/WHEEL
ably-2.1.3.dist-info/entry_points.txt
ably-2.1.3.dist-info/licenses/LICENSE
ably-2.1.3.dist-info/RECORD
